pystk.cpython-310-darwin.so
PySuperTuxKart-1.1.2.dist-info/COPYING
PySuperTuxKart-1.1.2.dist-info/METADATA
PySuperTuxKart-1.1.2.dist-info/WHEEL
PySuperTuxKart-1.1.2.dist-info/top_level.txt
PySuperTuxKart-1.1.2.dist-info/RECORD
