Metadata-Version: 2.1
Name: PySuperTuxKart
Version: 1.1.2
Summary: Python SuperTuxKart inferface
Home-page: https://github.com/philkr/pystk
Author: Philipp Krähenbühl
Author-email: philkr@utexas.edu
License: UNKNOWN
Platform: UNKNOWN
Classifier: Development Status :: 4 - Beta
Classifier: Environment :: Console
Classifier: Intended Audience :: Education
Classifier: Intended Audience :: Science/Research
Classifier: License :: OSI Approved :: GNU General Public License v3 (GPLv3)
Classifier: Programming Language :: Python :: 3
Classifier: Programming Language :: Python :: 3.6
Classifier: Programming Language :: Python :: 3.7
Classifier: Programming Language :: Python :: 3.8
Classifier: Topic :: Scientific/Engineering
Classifier: Topic :: Scientific/Engineering :: Artificial Intelligence
Requires-Python: >=3.6
License-File: COPYING
Requires-Dist: PySuperTuxKartData
